cookie06/__init__.py
cookie06/_version.py
cookie06/run_cookie06.py
cookie06-0.1.1.dist-info/DESCRIPTION.rst
cookie06-0.1.1.dist-info/METADATA
cookie06-0.1.1.dist-info/RECORD
cookie06-0.1.1.dist-info/WHEEL
cookie06-0.1.1.dist-info/entry_points.txt
cookie06-0.1.1.dist-info/metadata.json
cookie06-0.1.1.dist-info/top_level.txt
