Metadata-Version: 2.0
Name: cookie06
Version: 0.1.1
Summary: tmp
Home-page: https://github.com/grzanka/python-cookie06
Author: Leszek Grzanka
Author-email: grzanka@agh.edu.pl
License: GPL
Platform: UNKNOWN
Classifier: Development Status :: 3 - Alpha
Classifier: Intended Audience :: Developers
Classifier: Topic :: Software Development :: Build Tools
Classifier: License :: OSI Approved :: MIT License
Classifier: Programming Language :: Python :: 3.2
Classifier: Programming Language :: Python :: 3.3
Classifier: Programming Language :: Python :: 3.4
